api_24ur/__init__.py
api_24ur/client.py
api_24ur/downloader.py
api_24ur/exceptions.py
api_24ur/schemas.py
api_24ur/types.py
24ur_api-0.2.5.dist-info/METADATA
24ur_api-0.2.5.dist-info/WHEEL
24ur_api-0.2.5.dist-info/licenses/LICENSE
24ur_api-0.2.5.dist-info/RECORD
