Metadata-Version: 2.4
Name: 24ur-api
Version: 0.2.5
Summary: Unofficial 24ur API
Project-URL: Homepage, https://github.com/amadejkastelic/24ur-api
Project-URL: Source, https://github.com/amadejkastelic/24ur-api
Project-URL: Tracker, https://github.com/amadejkastelic/24ur-api/issues
Author-email: Amadej Kastelic <amadejkastelic7@gmail.com>
License: MIT
License-File: LICENSE
Keywords: 24ur,api,scraper
Requires-Python: ~=3.8
Requires-Dist: aiohttp<4
Provides-Extra: dev
Requires-Dist: packaging; extra == 'dev'
Requires-Dist: ruff; extra == 'dev'
Provides-Extra: video
Requires-Dist: yt-dlp; extra == 'video'
